macos_speech/__init__.py
macos_speech/macos_speech.py
macos_speech-1.1.0.dist-info/LICENSE
macos_speech-1.1.0.dist-info/METADATA
macos_speech-1.1.0.dist-info/WHEEL
macos_speech-1.1.0.dist-info/top_level.txt
macos_speech-1.1.0.dist-info/RECORD
