Metadata-Version: 2.1
Name: macos-speech
Version: 1.1.0
Summary: Leverage the macOS `say` command into you scripts
Home-page: https://github.com/tibOin/macos_speech/
Author: tibOin
Author-email: tiboin@protonmail.com
License: MIT
Keywords: macos,say,speech synthesis
Platform: UNKNOWN
Classifier: Development Status :: 5 - Production/Stable
Classifier: License :: OSI Approved :: MIT License
Classifier: Operating System :: MacOS
Classifier: Programming Language :: Python :: 2.7
Classifier: Programming Language :: Python :: 3
Classifier: Intended Audience :: Developers
Classifier: Intended Audience :: Education
Classifier: Topic :: Multimedia :: Sound/Audio
Classifier: Topic :: System :: Operating System
Classifier: Topic :: Utilities
